{"rightAltIsAltGr":true,"shiftCancelsCapsLock":false,"charMap":{"0":39,"1":30,"2":31,"3":32,"4":33,"5":34,"6":35,"7":36,"8":37,"9":38," ":44,",":54,"-":45,".":55,"ം":27,"ക":14,"ഗ":12,"ച":51,"ജ":19,"ട":52,"ഡ":47,"ത":15,"ദ":18,"ന":25,"പ":11,"ബ":28,"മ":6,"യ":56,"ര":13,"ല":17,"വ":5,"സ":16,"ഹ":24,"ാ":8,"ി":9,"ീ":21,"ു":10,"ൂ":23,"ൃ":46,"െ":29,"േ":22,"ൈ":26,"ൊ":53,"ോ":4,"ൌ":20,"്":7,"ർ":48,"(":[[225,38]],")":[[225,39]],"ഃ":[[225,45]],"അ":[[225,7]],"ആ":[[225,8]],"ഇ":[[225,9]],"ഈ":[[225,21]],"ഉ":[[225,10]],"ഊ":[[225,23]],"ഋ":[[225,46]],"എ":[[225,29]],"ഏ":[[225,22]],"ഐ":[[225,26]],"ഒ":[[225,53]],"ഓ":[[225,4]],"ഔ":[[225,20]],"ക്ഷ":[[225,36]],"ഖ":[[225,14]],"ഘ":[[225,12]],"ങ":[[225,24]],"ഛ":[[225,51]],"ഝ":[[225,19]],"ഞ":[[225,48]],"ഠ":[[225,52]],"ഢ":[[225,47]],"ണ":[[225,6]],"ഥ":[[225,15]],"ധ":[[225,18]],"ഫ":[[225,11]],"ഭ":[[225,28]],"റ":[[225,13]],"ള":[[225,17]],"ഴ":[[225,5]],"ശ":[[225,16]],"ഷ":[[225,54]],"്ര":[[225,32]],"ൺ":[[225,27]],"ൻ":[[225,25]],"ൽ":[[225,55]],"ൾ":[[225,37]],"ൿ":[[225,35]],"ൗ":[[230,20]],"൦":[[230,39]],"൧":[[230,30]],"൨":[[230,31]],"൩":[[230,32]],"൪":[[230,33]],"൫":[[230,34]],"൬":[[230,35]],"൭":[[230,36]],"൮":[[230,37]],"൯":[[230,38]],"‌":[[225,224,31]],"‍":[[225,224,30]],"₹":[[225,224,33]],"ഌ":[[225,230,7]],"ൠ":[[225,230,46]],"ൡ":[[225,230,21]],"൰":[[225,230,30]],"൱":[[225,230,31]],"൲":[[225,230,32]],"൹":[[225,230,25]]}}